numpyai/__init__.py
numpyai/py.typed
numpyai/backend/__init__.py
numpyai/backend/progress_bar.py
numpyai/backend/registrable.py
numpyai/backend/representable.py
numpyai/backend/utils.py
numpyai/feature_extraction/__init__.py
numpyai/feature_extraction/count_vectoriser.py
numpyai/nn/__init__.py
numpyai/nn/network.py
numpyai/nn/activations/__init__.py
numpyai/nn/activations/activation.py
numpyai/nn/activations/leaky_relu.py
numpyai/nn/activations/linear.py
numpyai/nn/activations/relu.py
numpyai/nn/activations/sigmoid.py
numpyai/nn/activations/softmax.py
numpyai/nn/activations/tanh.py
numpyai/nn/backend/__init__.py
numpyai/nn/backend/activations.py
numpyai/nn/backend/losses.py
numpyai/nn/backend/regularisers.py
numpyai/nn/datasets/__init__.py
numpyai/nn/datasets/dataset.py
numpyai/nn/datasets/mnist.py
numpyai/nn/datasets/utils.py
numpyai/nn/initialisers/__init__.py
numpyai/nn/initialisers/constant.py
numpyai/nn/initialisers/glorot.py
numpyai/nn/initialisers/he.py
numpyai/nn/initialisers/initialiser.py
numpyai/nn/initialisers/random.py
numpyai/nn/layers/__init__.py
numpyai/nn/layers/averagepooling2d.py
numpyai/nn/layers/conv2d.py
numpyai/nn/layers/dense.py
numpyai/nn/layers/dropout.py
numpyai/nn/layers/flatten.py
numpyai/nn/layers/layer.py
numpyai/nn/layers/maxpooling2d.py
numpyai/nn/layers/trainable_layer.py
numpyai/nn/losses/__init__.py
numpyai/nn/losses/binary_crossentropy.py
numpyai/nn/losses/categorical_crossentropy.py
numpyai/nn/losses/loss.py
numpyai/nn/losses/mean_absolute_error.py
numpyai/nn/losses/mean_squared_error.py
numpyai/nn/metrics/__init__.py
numpyai/nn/metrics/accuracy.py
numpyai/nn/metrics/binary_accuracy.py
numpyai/nn/metrics/binary_crossentropy.py
numpyai/nn/metrics/categorical_accuracy.py
numpyai/nn/metrics/categorical_crossentropy.py
numpyai/nn/metrics/mean_absolute_error.py
numpyai/nn/metrics/mean_squared_error.py
numpyai/nn/metrics/metric.py
numpyai/nn/metrics/root_mean_squared_error.py
numpyai/nn/optimisers/__init__.py
numpy_ai_kit-0.1.4.dist-info/METADATA
numpy_ai_kit-0.1.4.dist-info/WHEEL
numpy_ai_kit-0.1.4.dist-info/licenses/LICENSE
numpy_ai_kit-0.1.4.dist-info/RECORD
