Metadata-Version: 2.4
Name: numpy-ai-kit
Version: 0.1.4
Summary: A complete artificial intelligence kit built from scratch using Numpy.
Project-URL: Homepage, https://github.com/benjaminrall/numpy-ai-kit
Project-URL: Wiki, https://github.com/benjaminrall/numpy-ai-kit/wiki
Author-email: Benjamin Rall <benr2508@aol.com>
License-File: LICENSE
Classifier: License :: OSI Approved :: MIT License
Classifier: Operating System :: OS Independent
Classifier: Programming Language :: Python :: 3
Requires-Python: >=3.11
Requires-Dist: numpy>=2.3.2
